tgmsg/__init__.py
tgmsg/errors.py
tgmsg/tg_client.py
tgmsg/models/__init__.py
tgmsg/models/keyboards.py
tgmsg/models/messages.py
tgmsg/models/requests.py
tgmsg-0.0.1.dist-info/LICENSE
tgmsg-0.0.1.dist-info/METADATA
tgmsg-0.0.1.dist-info/WHEEL
tgmsg-0.0.1.dist-info/top_level.txt
tgmsg-0.0.1.dist-info/RECORD
