Metadata-Version: 2.1
Name: tgmsg
Version: 0.0.1
Summary: Simple but yet functional library for building Telegram bots
Home-page: https://github.com/AppVelox/tgmsg
Author: Appvelox LLC
Author-email: team@appvelox.ru
License: UNKNOWN
Platform: UNKNOWN
Classifier: Intended Audience :: Developers
Classifier: Programming Language :: Python :: 3.6
Classifier: License :: OSI Approved :: MIT License
Classifier: Operating System :: OS Independent
Requires-Python: >=3.6
Requires-Dist: requests
